whisk/__about__.py
whisk/__init__.py
whisk/__main__.py
whisk/client.py
whisk/config.py
whisk/dependencies.py
whisk/router.py
whisk/api/__init__.py
whisk/api/chat.py
whisk/api/commands.py
whisk/api/files.py
whisk/api/models.py
whisk/cli/__init__.py
whisk/cli/client.py
whisk/cli/init.py
whisk/cli/nats.py
whisk/cli/run.py
whisk/cli/serve.py
whisk/cli/version.py
whisk/examples/__init__.py
whisk/examples/agent.py
whisk/examples/app.py
whisk/kitchenai_sdk/__init__.py
whisk/kitchenai_sdk/base.py
whisk/kitchenai_sdk/http_schema.py
whisk/kitchenai_sdk/kitchenai.py
whisk/kitchenai_sdk/nats_schema.py
whisk/kitchenai_sdk/schema.py
whisk/kitchenai_sdk/taxonomy/__init__.py
whisk/kitchenai_sdk/taxonomy/agent.py
whisk/kitchenai_sdk/taxonomy/chat.py
whisk/kitchenai_sdk/taxonomy/embeddings.py
whisk/kitchenai_sdk/taxonomy/query.py
whisk/kitchenai_sdk/taxonomy/storage.py
kitchenai_whisk-0.2.3.dist-info/METADATA
kitchenai_whisk-0.2.3.dist-info/WHEEL
kitchenai_whisk-0.2.3.dist-info/entry_points.txt
kitchenai_whisk-0.2.3.dist-info/RECORD
