Metadata-Version: 2.4
Name: kitchenai-whisk
Version: 0.2.3
Summary: KitchenAI Whisk - Whisk Up Your Bento Box. A tool for running kitchenai apps.
License-Expression: MIT
Requires-Python: >=3.11
Requires-Dist: anyio>=3.7.1
Requires-Dist: cookiecutter>=2.5.0
Requires-Dist: fastapi>=0.100.0
Requires-Dist: faststream[nats]>=0.4.0
Requires-Dist: httpx>=0.26.0
Requires-Dist: pydantic>=2.0.0
Requires-Dist: python-multipart
Requires-Dist: pyyaml>=6.0.0
Requires-Dist: rich>=13.7.0
Requires-Dist: typer>=0.9.0
Requires-Dist: uvicorn>=0.27.0
Requires-Dist: watchfiles
Provides-Extra: test
Requires-Dist: httpx>=0.26.0; extra == 'test'
Requires-Dist: pytest-asyncio>=0.23.0; extra == 'test'
Requires-Dist: pytest-cov>=4.1.0; extra == 'test'
Requires-Dist: pytest>=7.0.0; extra == 'test'
